pytictoc.py
pytictoc-1.5.2.dist-info/LICENSE.txt
pytictoc-1.5.2.dist-info/METADATA
pytictoc-1.5.2.dist-info/WHEEL
pytictoc-1.5.2.dist-info/top_level.txt
pytictoc-1.5.2.dist-info/RECORD
