Metadata-Version: 1.1
Name: pytictoc
Version: 1.5.2
Summary: Time code using syntax similar to tic and toc in MATLAB
Home-page: https://github.com/ericcfields/pytictoc
Author: Eric Fields
Author-email: eric.fields@bc.edu
License: BSD (three-clause)
Keywords: timing tic toc MATLAB
Platform: UNKNOWN
Classifier: Development Status :: 5 - Production/Stable
Classifier: Intended Audience :: Developers
Classifier: Topic :: Software Development :: Testing
Classifier: License :: OSI Approved :: BSD License
Classifier: Programming Language :: Python :: 2
Classifier: Programming Language :: Python :: 3
